{
  "version": "3.2.0",
  "mape": 7.165057957172394,
  "r2": 0.770727276802063,
  "config": {
    "input_hours": 96,
    "hidden_size": 64,
    "num_layers": 1,
    "dropout": 0.198,
    "n_heads": 4,
    "learning_rate": 0.000165,
    "weight_decay": 0.000476,
    "batch_size": 32,
    "noise_std": 0.01,
    "max_epochs": 150,
    "output_hours": 24
  },
  "features": [
    "smp_mainland",
    "smp_jeju",
    "smp_max",
    "smp_min",
    "hour_sin",
    "hour_cos",
    "dow_sin",
    "dow_cos",
    "is_weekend",
    "month_sin",
    "month_cos",
    "is_summer",
    "is_winter",
    "peak_morning",
    "peak_evening",
    "off_peak",
    "smp_ma24",
    "smp_std24",
    "smp_diff",
    "smp_range",
    "smp_lag_24h",
    "smp_lag_168h"
  ],
  "n_features": 22,
  "model_file": "smp_v32_model.pt",
  "scaler_file": "smp_v32_scaler.pkl",
  "timestamp": "2025-12-26T17:21:35.457046"
}